Workbook

Sheet How to use
B1: Lead Leak Calculator
B2: Bonus to The Lead Leak Kit, by Hemant Kumar · askhemant.ai · @askhemant
B4: What it does
B5: It turns your own numbers into an estimate of how many enquiries pass through a leak each month (late reply, no follow-up, no-shows) and what those enquiries are worth at your own close rate.
B6: Your numbers, your estimate. Not a promise, not a forecast. AskHemant supplies no ROI figures.
B8: How to use it (5 minutes)
B9: 1. Open the "Your numbers" tab. Change only the yellow cells. The numbers already there are examples to show how it works, not benchmarks. Type percentages with the % sign (30%).
B10: 2. Not sure of a number? Count last month's enquiries in your phone, inbox and portal dashboards. For reply speed, do the 10 pm self-test (kit page 11).
B11: 3. Open "Results". Check "Revenue per month now" first. If it doesn't match your real income, fix your close rate or deal value before reading anything else.
B12: 4. The win-back lines stay empty until you type YOUR guess in yellow input 11. Start low.
B13: 5. Want a second opinion on your numbers? Book a free 20-min Fit Call at askhemant.ai/book.
B14: Using it in Google Sheets
... B21: v1 · October 2026 · General guidance, not financial advice.

Sheet Your numbers
B1: Your numbers
B2: Change the yellow cells only. Your numbers, your estimate. Not a promise.
B3: The values below are EXAMPLES. Replace every one with your own.
A5: # | B5: Your number | C5: Value | D5: How to find it
A6: 1 | B6: Enquiries per month, all sources | C6: 120 | D6: Count last month: portal alerts, Meta leads, Instagram DMs, WhatsApp chats, calls.
A7: 2 | B7: Share that arrive after hours (e.g. after 8 pm, before 9 am, Sundays) | C7: 0.3 | D7: Check the timestamps on last month's enquiries.
A8: 3 | B8: Of those after-hours enquiries: share first answered next day or later | C8: 0.8 | D8: Your 10 pm self-test (kit page 11) is a good first measure.
A9: 4 | B9: Of daytime enquiries: share first answered after more than 1 hour | C9: 0.3 | D9: Think of site-visit days, drives and meetings.
A10: 5 | B10: Share of enquiries never followed up after day 2 | C10: 0.5 | D10: Scroll your WhatsApp: how many chats stop after one call?
A11: 6 | B11: Share of enquiries that book a site visit (or appointment) | C11: 0.1 | D11: Visits booked last month / enquiries last month.
A12: 7 | B12: Share of booked visits that don't show up | C12: 0.2 | D12: No-shows / visits booked.
A13: 8 | B13: Current close rate: share of enquiries that become a deal | C13: 0.02 | D13: Deals closed in the last 6 months / enquiries in the same 6 months.
A14: 9 | B14: Average deal value, or your commission per deal | C14: 150000 | D14: Brokers: use your commission, not the property price.
A15: 10 | B15: Hours lost per no-show (travel + waiting) | C15: 2 | D15: Your time, round trip.
A16: 11 | B16: YOUR GUESS: share of at-risk deals you could win back with faster, steadier follow-up | D16: Left blank on purpose. Only you can guess this; start low. Nobody can promise it.
A17: 12 | B17: Optional: one-off cost of a fix you're considering | D17: Leave blank if none. Used only for the break-even lines.
A18: 13 | B18: Currency label | C18: ₹ | D18: Type $ or AED if you prefer. It only changes the labels.
B20: Next: open the Results tab.

Sheet Results
B1: Results
B2: Your numbers, your estimate. Not a promise.
B3: =IF(AND('Your numbers'!$C$6=120,'Your numbers'!$C$7=0.3,'Your numbers'!$C$8=0.8,'Your numbers'!$C$9=0.3,'Your numbers'!$C$10=0.5,'Your numbers'!$C$11=0.1,'Your numbers'!$C$12=0.2,'Your numbers'!$C$13=0.02,'Your numbers'!$C$14=150000),"These are still the EXAMPLE numbers. Change the yellow cells on Your numbers.","Based on your numbers.")
B6: A. Where your enquiries leak (per month) | E6: How it's calculated (numbers = inputs on Your numbers)
B7: Enquiries per month | C7: ='Your numbers'!$C$6 | E7: Input 1
B8: After-hours enquiries | C8: ='Your numbers'!$C$6*'Your numbers'!$C$7 | E8: 1 × 2
B9: …first answered next day or later | C9: ='Your numbers'!$C$6*'Your numbers'!$C$7*'Your numbers'!$C$8 | E9: 1 × 2 × 3
B10: Daytime enquiries answered after more than 1 hour | C10: ='Your numbers'!$C$6*(1-'Your numbers'!$C$7)*'Your numbers'!$C$9 | E10: 1 × (100% − 2) × 4
B11: Total enquiries answered late | C11: =C9+C10 | E11: The two lines above
B12: Share answered late | C12: =IFERROR(C11/C7,0) | E12: Late ÷ all enquiries
B13: Never followed up after day 2 | C13: ='Your numbers'!$C$6*'Your numbers'!$C$10 | E13: 1 × 5
B14: Enquiries at risk (late reply, no follow-up, or both) | C14: ='Your numbers'!$C$6*(1-(1-C12)*(1-'Your numbers'!$C$10)) | E14: 1 × [100% − (100% − late share) × (100% − 5)]. Counted once if hit by both.
B15: Booked visits that don't show up | C15: ='Your numbers'!$C$6*'Your numbers'!$C$11*'Your numbers'!$C$12 | E15: 1 × 6 × 7
B16: Hours lost to no-shows | C16: =C15*'Your numbers'!$C$15 | D16: hrs | E16: No-shows × 10
B18: B. What that's worth, at your own close rate | E18: How it's calculated (numbers = inputs on Your numbers)
B19: Deals per month now | C19: ='Your numbers'!$C$6*'Your numbers'!$C$13 | E19: 1 × 8
B20: Revenue per month now (check: does this match reality?) | C20: =C19*'Your numbers'!$C$14 | D20: ='Your numbers'!$C$18 | E20: Deals × 9. If this is far from your real income, adjust 8 or 9 first.
B21: Deals that pass through a leak each month | C21: =C14*'Your numbers'!$C$13 | E21: At-risk enquiries × 8
B22: Revenue at risk per month | C22: =C21*'Your numbers'!$C$14 | D22: ='Your numbers'!$C$18 | E22: Deals through a leak × 9
B23: Revenue at risk per year | C23: =C22*12 | D23: ='Your numbers'!$C$18 | E23: × 12
B25: C. Your what-if (uses YOUR guess, input 11) | E25: How it's calculated (numbers = inputs on Your numbers)
B26: Deals won back per month, if your guess holds | C26: =IF('Your numbers'!$C$16="","Enter input 11 first",C21*'Your numbers'!$C$16) | E26: Deals through a leak × 11
B27: Revenue won back per month, if your guess holds | C27: =IF('Your numbers'!$C$16="","—",C26*'Your numbers'!$C$14) | D27: ='Your numbers'!$C$18 | E27: Deals won back × 9
B28: Revenue won back per year, if your guess holds | C28: =IF('Your numbers'!$C$16="","—",C27*12) | D28: ='Your numbers'!$C$18 | E28: × 12
B29: Extra deals that would cover the fix cost | C29: =IF(OR('Your numbers'!$C$17="",'Your numbers'!$C$14=0),"—",'Your numbers'!$C$17/'Your numbers'!$C$14) | E29: 12 ÷ 9 (break-even, no guess needed)
B30: Months to cover the fix cost, if your guess holds | C30: =IF(OR('Your numbers'!$C$17="",'Your numbers'!$C$16="",'Your numbers'!$C$16=0,'Your numbers'!$C$13=0,'Your numbers'!$C$14=0,'Your numbers'!$C$6=0),"—",'Your numbers'!$C$17/C27) | D30: months | E30: 12 ÷ monthly revenue won back
B32: Assumptions, in plain words
B33: 1. "At risk" means an enquiry hit at least one leak. It does not mean it was lost.
B34: 2. A late reply and no follow-up are treated as independent, so an enquiry hit by both is counted once.
B35: 3. Money at risk uses your current close rate for every enquiry. Fast-answered leads may close better or worse.
B36: 4. The win-back lines use only your own guess (input 11). AskHemant supplies no ROI figure, and nothing here is a promise or forecast.
B37: 5. No-shows are shown as a count and hours; they are not added to the money lines, to avoid counting the same lead twice.
B38: 6. All amounts are before tax, in the currency label you chose (input 13).
B40: Want a second opinion on these numbers? Free 20-min Fit Call: askhemant.ai/book
